web_browser_mcp_server/__init__.py
web_browser_mcp_server/__main__.py
web_browser_mcp_server/config.py
web_browser_mcp_server/server.py
iflow_mcp_web_browser_mcp_server-0.2.2.dist-info/METADATA
iflow_mcp_web_browser_mcp_server-0.2.2.dist-info/WHEEL
iflow_mcp_web_browser_mcp_server-0.2.2.dist-info/entry_points.txt
iflow_mcp_web_browser_mcp_server-0.2.2.dist-info/licenses/LICENSE
iflow_mcp_web_browser_mcp_server-0.2.2.dist-info/RECORD
